Workbook

Sheet 3 Statement Model
B2: 3 Statement Financial Model
B3: SCENARIO | C3: Revnue | D3: Payroll | E3: CAPEX
B4: Best | C4: =INDEX(Assumptions!B3:B5,MATCH('3 Statement Model'!B4,Assumptions!A3:A5,0)) -> 0.2 | D4: =INDEX(Assumptions!C3:C5,MATCH('3 Statement Model'!B4,Assumptions!A3:A5,0)) -> 0 | E4: =INDEX(Assumptions!D3:D5,MATCH('3 Statement Model'!B4,Assumptions!A3:A5,0)) -> 0
B6: Income Statement
D7: 46023 | E7: 46054 | F7: 46082 | G7: 46113 | H7: 46143 | I7: 46174 | J7: 46204 | K7: 46235 | L7: 46266 | M7: 46296 | N7: 46327 | O7: 46357
B8: Revenue | D8: =INDEX('Financial Forecast'!$B$2:$B$13,MATCH('3 Statement Model'!D7,'Financial Forecast'!$A$2:$A$13,0)) -> 1380000 | E8: =INDEX('Financial Forecast'!$B$2:$B$13,MATCH('3 Statement Model'!E7,'Financial Forecast'!$A$2:$A$13,0)) -> 1931454 | F8: =INDEX('Financial Forecast'!$B$2:$B$13,MATCH('3 Statement Model'!F7,'Financial Forecast'!$A$2:$A$13,0)) -> 2122909.2 | G8: =INDEX('Financial Forecast'!$B$2:$B$13,MATCH('3 Statement Model'!G7,'Financial Forecast'!$A$2:$A$13,0)) -> 2314363.2 | H8: =INDEX('Financial Forecast'!$B$2:$B$13,MATCH('3 Statement Model'!H7,'Financial Forecast'!$A$2:$A$13,0)) -> 2505818.4 | I8: =INDEX('Financial Forecast'!$B$2:$B$13,MATCH('3 Statement Model'!I7,'Financial Forecast'!$A$2:$A$13,0)) -> 2535272.4 | J8: =INDEX('Financial Forecast'!$B$2:$B$13,MATCH('3 Statement Model'!J7,'Financial Forecast'!$A$2:$A$13,0)) -> 2564727.6 | K8: =INDEX('Financial Forecast'!$B$2:$B$13,MATCH('3 Statement Model'!K7,'Financial Forecast'!$A$2:$A$13,0)) -> 2594181.6 | ... O8: =INDEX('Financial Forecast'!$B$2:$B$13,MATCH('3 Statement Model'!O7,'Financial Forecast'!$A$2:$A$13,0)) -> 2712000
B10: OPEX | D10: ='Financial Forecast'!G2 -> 1254293.6 | E10: ='Financial Forecast'!G3 -> 1269516.1 | F10: ='Financial Forecast'!G4 -> 1283729 | G10: ='Financial Forecast'!G5 -> 1279774 | H10: ='Financial Forecast'!G6 -> 1284320 | I10: ='Financial Forecast'!G7 -> 1288865 | J10: ='Financial Forecast'!G8 -> 1293411 | K10: ='Financial Forecast'!G9 -> 1297956 | L10: ='Financial Forecast'!G10 -> 1302502 | M10: ='Financial Forecast'!G11 -> 1307047 | N10: ='Financial Forecast'!G12 -> 1311593 | O10: ='Financial Forecast'!G13 -> 1316138
B11: EBITDA | D11: ='Financial Forecast'!H2 -> 125706.39 | E11: ='Financial Forecast'!H3 -> 661937.89 | F11: ='Financial Forecast'!H4 -> 839180.18 | G11: ='Financial Forecast'!H5 -> 1034589.2 | H11: ='Financial Forecast'!H6 -> 1221498.4 | I11: ='Financial Forecast'!H7 -> 1246407.4 | J11: ='Financial Forecast'!H8 -> 1271316.6 | K11: ='Financial Forecast'!H9 -> 1296225.6 | L11: ='Financial Forecast'!H10 -> 1321134.8 | M11: ='Financial Forecast'!H11 -> 903861.98 | N11: ='Financial Forecast'!H12 -> 1370953 | O11: ='Financial Forecast'!H13 -> 1395862
B12: Depreciation | D12: =CAPEX!A20 -> 3333.3333 | E12: =CAPEX!B20 -> 3666.6667 | F12: =CAPEX!C20 -> 4000 | G12: =CAPEX!D20 -> 4333.3333 | H12: =CAPEX!E20 -> 4666.6667 | I12: =CAPEX!F20 -> 5000 | J12: =CAPEX!G20 -> 5333.3333 | K12: =CAPEX!H20 -> 5666.6667 | ... O12: =CAPEX!L20 -> 7000
B13: Interest | D13: ='Financing and Funding Analysis'!D3 -> 3333.3333 | E13: ='Financing and Funding Analysis'!D4 -> 3204.7979 | F13: ='Financing and Funding Analysis'!D5 -> 3075.4056 | G13: ='Financing and Funding Analysis'!D6 -> 2945.1507 | H13: ='Financing and Funding Analysis'!D7 -> 2814.0274 | I13: ='Financing and Funding Analysis'!D8 -> 2682.0299 | J13: ='Financing and Funding Analysis'!D9 -> 2549.1525 | K13: ='Financing and Funding Analysis'!D10 -> 2415.3892 | L13: ='Financing and Funding Analysis'!D11 -> 2280.7341 | M13: ='Financing and Funding Analysis'!D12 -> 2145.1814 | N13: ='Financing and Funding Analysis'!D13 -> 2008.725 | O13: ='Financing and Funding Analysis'!D14 -> 1871.3588
B14: EBIT | D14: =D11-D12 -> 122373.05 | E14: =E11-E12 -> 658271.22 | F14: =F11-F12 -> 835180.18 | G14: =G11-G12 -> 1030255.8 | H14: =H11-H12 -> 1216831.7 | I14: =I11-I12 -> 1241407.4 | J14: =J11-J12 -> 1265983.2 | K14: =K11-K12 -> 1290558.9 | ... O14: =O11-O12 -> 1388862
B15: Taxes | D15: =D14*0.3 -> 36711.916 | E15: =E14*0.3 -> 197481.37 | F15: =F14*0.3 -> 250554.05 | G15: =G14*0.3 -> 309076.75 | H15: =H14*0.3 -> 365049.51 | I15: =I14*0.3 -> 372422.21 | J15: =J14*0.3 -> 379794.97 | K15: =K14*0.3 -> 387167.67 | ... O15: =O14*0.3 -> 416658.59
B16: Net Income | D16: =D14-D15 -> 85661.136 | E16: =E14-E15 -> 460789.85 | F16: =F14-F15 -> 584626.13 | G16: =G14-G15 -> 721179.09 | H16: =H14-H15 -> 851782.2 | I16: =I14-I15 -> 868985.17 | J16: =J14-J15 -> 886188.27 | K16: =K14-K15 -> 903391.24 | ... O16: =O14-O15 -> 972203.39
B19: Balance Sheet
D20: 46023 | E20: 46054 | F20: 46082 | G20: 46113 | H20: 46143 | I20: 46174 | J20: 46204 | K20: 46235 | L20: 46266 | M20: 46296 | N20: 46327 | O20: 46357
B21: Cash & Cash Equivalents | D21: =D44 -> 569714.16 | E21: =E44 -> 994761.83 | F21: =F44 -> 1543849.7 | G21: =G44 -> 2229693.6 | H21: =H44 -> 3046342.9 | I21: =I44 -> 3880396.4 | J21: =J44 -> 4731853.6 | K21: =K44 -> 5600713.2 | ... O21: =O44 -> 8940632.8
B22: Net Fixed Asset (NBV) | D22: =CAPEX!A24 -> 196666.67 | E22: =CAPEX!B24 -> 213000 | F22: =CAPEX!C24 -> 229000 | G22: =CAPEX!D24 -> 244666.67 | H22: =CAPEX!E24 -> 260000 | I22: =CAPEX!F24 -> 275000 | J22: =CAPEX!G24 -> 289666.67 | K22: =CAPEX!H24 -> 304000 | ... O22: =CAPEX!L24 -> 358000
B24: Total Assets | D24: =D21+D22 -> 766380.82 | E24: =E21+E22 -> 1207761.8 | F24: =F21+F22 -> 1772849.7 | G24: =G21+G22 -> 2474360.3 | H24: =H21+H22 -> 3306342.9 | I24: =I21+I22 -> 4155396.4 | J24: =J21+J22 -> 5021520.2 | K24: =K21+K22 -> 5904713.2 | ... O24: =O21+O22 -> 9298632.8
B26: Loan Balance | D26: ='Financing and Funding Analysis'!C4 -> 480719.69 | E26: ='Financing and Funding Analysis'!C5 -> 461310.84 | F26: ='Financing and Funding Analysis'!C6 -> 441772.6 | G26: ='Financing and Funding Analysis'!C7 -> 422104.1 | H26: ='Financing and Funding Analysis'!C8 -> 402304.49 | I26: ='Financing and Funding Analysis'!C9 -> 382372.87 | J26: ='Financing and Funding Analysis'!C10 -> 362308.38 | K26: ='Financing and Funding Analysis'!C11 -> 342110.12 | L26: ='Financing and Funding Analysis'!C12 -> 321777.21 | M26: ='Financing and Funding Analysis'!C13 -> 301308.74 | N26: ='Financing and Funding Analysis'!C14 -> 280703.82 | O26: ='Financing and Funding Analysis'!C14-'Financing and Funding Analysis'!E14 -> 259961.54
B27: Total Liabilities | D27: =SUM(D26:D26) -> 480719.69 | E27: =SUM(E26:E26) -> 461310.84 | F27: =SUM(F26:F26) -> 441772.6 | G27: =SUM(G26:G26) -> 422104.1 | H27: =SUM(H26:H26) -> 402304.49 | I27: =SUM(I26:I26) -> 382372.87 | J27: =SUM(J26:J26) -> 362308.38 | K27: =SUM(K26:K26) -> 342110.12 | ... O27: =SUM(O26:O26) -> 259961.54
B29: Share Capital | D29: =Financing!B3 -> 200000 | E29: =D29 -> 200000 | F29: =E29 -> 200000 | G29: =F29 -> 200000 | H29: =G29 -> 200000 | I29: =H29 -> 200000 | J29: =I29 -> 200000 | K29: =J29 -> 200000 | L29: =K29 -> 200000 | ... O29: =N29 -> 200000
B30: Retained Earnings | D30: =D16 -> 85661.136 | E30: =D30+E16 -> 546450.99 | F30: =E30+F16 -> 1131077.1 | G30: =F30+G16 -> 1852256.2 | H30: =G30+H16 -> 2704038.4 | I30: =H30+I16 -> 3573023.6 | J30: =I30+J16 -> 4459211.9 | K30: =J30+K16 -> 5362603.1 | L30: =K30+L16 -> 6283197.4 | ... O30: =N30+O16 -> 8838671.3
B31: Total Shareolders Equity | D31: =SUM(D29:D30) -> 285661.14 | E31: =SUM(E29:E30) -> 746450.99 | F31: =SUM(F29:F30) -> 1331077.1 | G31: =SUM(G29:G30) -> 2052256.2 | H31: =SUM(H29:H30) -> 2904038.4 | I31: =SUM(I29:I30) -> 3773023.6 | J31: =SUM(J29:J30) -> 4659211.9 | K31: =SUM(K29:K30) -> 5562603.1 | ... O31: =SUM(O29:O30) -> 9038671.3
B33: Total Liabilities & Equity | D33: =D27+D31 -> 766380.82 | E33: =E27+E31 -> 1207761.8 | F33: =F27+F31 -> 1772849.7 | G33: =G27+G31 -> 2474360.3 | H33: =H27+H31 -> 3306342.9 | I33: =I27+I31 -> 4155396.4 | J33: =J27+J31 -> 5021520.2 | K33: =K27+K31 -> 5904713.2 | ... O33: =O27+O31 -> 9298632.8
D34: =D24-(D27+D31) -> 0 | E34: =E24-E33 -> 0 | F34: =F24-F33 -> 0 | G34: =G24-G33 -> 0 | H34: =H24-H33 -> 0 | I34: =I24-I33 -> 0 | J34: =J24-J33 -> 0 | K34: =K24-K33 -> 0 | L34: =L24-L33 -> 0 | ... O34: =O24-O33 -> 0
B36: Cash Flow Statement
D37: 46023 | E37: 46054 | F37: 46082 | G37: 46113 | H37: 46143 | I37: 46174 | J37: 46204 | K37: 46235 | L37: 46266 | M37: 46296 | N37: 46327 | O37: 46357
B38: Cash Flow in Operating Activities | D38: =D16+D12 -> 88994.47 | E38: =E16+E12 -> 464456.52 | F38: =F16+F12 -> 588626.13 | G38: =G16+G12 -> 725512.43 | H38: =H16+H12 -> 856448.87 | I38: =I16+I12 -> 873985.17 | J38: =J16+J12 -> 891521.61 | K38: =K16+K12 -> 909057.91 | ... O38: =O16+O12 -> 979203.39
B39: Cash Flow in Investing Activities | D39: =-'Financial Forecast'!E2 -> -200000 | E39: =-'Financial Forecast'!E3 -> -20000 | F39: =-'Financial Forecast'!E4 -> -20000 | G39: =-'Financial Forecast'!E6 -> -20000 | H39: =-'Financial Forecast'!E6 -> -20000 | I39: =-'Financial Forecast'!E7 -> -20000 | J39: =-'Financial Forecast'!E8 -> -20000 | K39: =-'Financial Forecast'!E9 -> -20000 | L39: =-'Financial Forecast'!E10 -> -20000 | M39: =-'Financial Forecast'!E11 -> -20000 | N39: =-'Financial Forecast'!E12 -> -20000 | O39: =-'Financial Forecast'!E13 -> -20000
B40: Cash Flow in Financing Activities | D40: ='Financing and Funding Analysis'!F3+'Financing and Funding Analysis'!C3-'Financing and Funding Analysis'!E3 -> 680719.69 | E40: =0+0-'Financing and Funding Analysis'!E4 -> -19408.848 | F40: =0+0-'Financing and Funding Analysis'!E5 -> -19538.24 | G40: =0+0-'Financing and Funding Analysis'!E6 -> -19668.495 | H40: =0+0-'Financing and Funding Analysis'!E7 -> -19799.618 | I40: =0+0-'Financing and Funding Analysis'!E8 -> -19931.616 | J40: =0+0-'Financing and Funding Analysis'!E9 -> -20064.493 | K40: =0+0-'Financing and Funding Analysis'!E10 -> -20198.257 | L40: =0+0-'Financing and Funding Analysis'!E11 -> -20332.912 | M40: =0+0-'Financing and Funding Analysis'!E12 -> -20468.464 | N40: =0+0-'Financing and Funding Analysis'!E13 -> -20604.921 | O40: =0+0-'Financing and Funding Analysis'!E14 -> -20742.287
B41: Opening Cash | D41: 0 | E41: =D44 -> 569714.16 | F41: =E44 -> 994761.83 | G41: =F44 -> 1543849.7 | H41: =G44 -> 2229693.6 | I41: =H44 -> 3046342.9 | J41: =I44 -> 3880396.4 | K41: =J44 -> 4731853.6 | L41: =K44 -> 5600713.2 | ... O41: =N44 -> 8002171.7
B42: Net Cash Movement | D42: =D38+D39+D40 -> 569714.16 | E42: =E38+E39+E40 -> 425047.67 | F42: =F38+F39+F40 -> 549087.89 | G42: =G38+G39+G40 -> 685843.93 | H42: =H38+H39+H40 -> 816649.25 | I42: =I38+I39+I40 -> 834053.55 | J42: =J38+J39+J40 -> 851457.11 | K42: =K38+K39+K40 -> 868859.65 | ... O42: =O38+O39+O40 -> 938461.1
B44: Closing Cash | D44: =D41+D42 -> 569714.16 | E44: =E41+E42 -> 994761.83 | F44: =F41+F42 -> 1543849.7 | G44: =G41+G42 -> 2229693.6 | H44: =H41+H42 -> 3046342.9 | I44: =I41+I42 -> 3880396.4 | J44: =J41+J42 -> 4731853.6 | K44: =K41+K42 -> 5600713.2 | ... O44: =O41+O42 -> 8940632.8

Sheet Financing and Funding Analysis
A2: Period | B2: FCF(Free Cash Flow) | C2: Loan Balance | D2: Interest | E2: Principal | F2: Equity Inflow | G2: Adjusted FCF | H2: Liquidity Flag
A3: 46023 | B3: ='Financial Forecast'!F2-'Financial Forecast'!E2 -> -340000 | C3: =Financing!B2 -> 500000 | D3: =Financing!C8 -> 3333.3333 | E3: =Financing!C9 -> 19280.312 | F3: =Financing!B3 -> 200000 | G3: =B3+F3-D3-E3 -> -162613.65 | H3: =IF(G3<0,"Liquidity Risk","No") -> Liquidity Risk
A4: 46054 | B4: ='Financial Forecast'!F3-'Financial Forecast'!E3 -> 27273 | C4: =C3-E3 -> 480719.69 | D4: =C4*0.08/12 -> 3204.7979 | E4: =Financing!$C$7-'Financing and Funding Analysis'!D4 -> 19408.848 | F4: =0 -> 0 | G4: =B4+F4-D4-E4 -> 4659.3543 | H4: =IF(G4<0,"Liquidity Risk","No") -> No
A5: 46082 | B5: ='Financial Forecast'!F4-'Financial Forecast'!E4 -> 34545 | C5: =C4-E4 -> 461310.84 | D5: =C5*0.08/12 -> 3075.4056 | E5: =Financing!$C$7-'Financing and Funding Analysis'!D5 -> 19538.24 | F5: =0 -> 0 | G5: =B5+F5-D5-E5 -> 11931.354 | H5: =IF(G5<0,"Liquidity Risk","No") -> No
A6: 46113 | B6: ='Financial Forecast'!F5-'Financial Forecast'!E5 -> 41818 | C6: =C5-E5 -> 441772.6 | D6: =C6*0.08/12 -> 2945.1507 | E6: =Financing!$C$7-'Financing and Funding Analysis'!D6 -> 19668.495 | F6: =0 -> 0 | G6: =B6+F6-D6-E6 -> 19204.354 | H6: =IF(G6<0,"Liquidity Risk","No") -> No
A7: 46143 | B7: ='Financial Forecast'!F6-'Financial Forecast'!E6 -> 49091 | C7: =C6-E6 -> 422104.1 | D7: =C7*0.08/12 -> 2814.0274 | E7: =Financing!$C$7-'Financing and Funding Analysis'!D7 -> 19799.618 | F7: =0 -> 0 | G7: =B7+F7-D7-E7 -> 26477.354 | H7: =IF(G7<0,"Liquidity Risk","No") -> No
A8: 46174 | B8: ='Financial Forecast'!F7-'Financial Forecast'!E7 -> 56364 | C8: =C7-E7 -> 402304.49 | D8: =C8*0.08/12 -> 2682.0299 | E8: =Financing!$C$7-'Financing and Funding Analysis'!D8 -> 19931.616 | F8: =0 -> 0 | G8: =B8+F8-D8-E8 -> 33750.354 | H8: =IF(G8<0,"Liquidity Risk","No") -> No
A9: 46204 | B9: ='Financial Forecast'!F8-'Financial Forecast'!E8 -> 63636 | C9: =C8-E8 -> 382372.87 | D9: =C9*0.08/12 -> 2549.1525 | E9: =Financing!$C$7-'Financing and Funding Analysis'!D9 -> 20064.493 | F9: =0 -> 0 | G9: =B9+F9-D9-E9 -> 41022.354 | H9: =IF(G9<0,"Liquidity Risk","No") -> No
A10: 46235 | B10: ='Financial Forecast'!F9-'Financial Forecast'!E9 -> 70909 | C10: =C9-E9 -> 362308.38 | D10: =C10*0.08/12 -> 2415.3892 | E10: =Financing!$C$7-'Financing and Funding Analysis'!D10 -> 20198.257 | F10: =0 -> 0 | G10: =B10+F10-D10-E10 -> 48295.354 | H10: =IF(G10<0,"Liquidity Risk","No") -> No
A11: 46266 | B11: ='Financial Forecast'!F10-'Financial Forecast'!E10 -> 78182 | C11: =C10-E10 -> 342110.12 | D11: =C11*0.08/12 -> 2280.7341 | E11: =Financing!$C$7-'Financing and Funding Analysis'!D11 -> 20332.912 | F11: =0 -> 0 | G11: =B11+F11-D11-E11 -> 55568.354 | H11: =IF(G11<0,"Liquidity Risk","No") -> No
A12: 46296 | B12: ='Financial Forecast'!F11-'Financial Forecast'!E11 -> 85455 | C12: =C11-E11 -> 321777.21 | D12: =C12*0.08/12 -> 2145.1814 | E12: =Financing!$C$7-'Financing and Funding Analysis'!D12 -> 20468.464 | F12: =0 -> 0 | G12: =B12+F12-D12-E12 -> 62841.354 | H12: =IF(G12<0,"Liquidity Risk","No") -> No
A13: 46327 | B13: ='Financial Forecast'!F12-'Financial Forecast'!E12 -> 92727 | C13: =C12-E12 -> 301308.74 | D13: =C13*0.08/12 -> 2008.725 | E13: =Financing!$C$7-'Financing and Funding Analysis'!D13 -> 20604.921 | F13: =0 -> 0 | G13: =B13+F13-D13-E13 -> 70113.354 | H13: =IF(G13<0,"Liquidity Risk","No") -> No
A14: 46357 | B14: ='Financial Forecast'!F13-'Financial Forecast'!E13 -> 100000 | C14: =C13-E13 -> 280703.82 | D14: =C14*0.08/12 -> 1871.3588 | E14: =Financing!$C$7-'Financing and Funding Analysis'!D14 -> 20742.287 | F14: =0 -> 0 | G14: =B14+F14-D14-E14 -> 77386.354 | H14: =IF(G14<0,"Liquidity Risk","No") -> No

Sheet Financial Forecast
A1: Period | B1: Revenue | C1: Payroll Cost | D1: Other OPEX | E1: CAPEX | F1: Operating Cash Flow | G1: Total OPEX | H1: EBIDA
A2: 46023 | B2: =(1150000+O9)*(1+'3 Statement Model'!C4) -> 1380000 | C2: =(1047456+T9)*(1+'3 Statement Model'!D4) -> 1112153.6 | D2: =110000+S9 -> 142140 | E2: =(200000)*(1+'3 Statement Model'!E4) -> 200000 | F2: -140000 | G2: =C2+D2 -> 1254293.6 | H2: =B2-G2 -> 125706.39
A3: 46054 | B3: =(1474545+O10)*(1+'3 Statement Model'!C4) -> 1931454 | C3: =(1047456+T10)*(1+'3 Statement Model'!D4) -> 1138471.1 | D3: =114545+S10 -> 131045 | E3: =(20000)*(1+'3 Statement Model'!E4) -> 20000 | F3: 47273 | G3: =C3+D3 -> 1269516.1 | H3: =B3-G3 -> 661937.89
A4: 46082 | B4: =(1499091+O11)*(1+'3 Statement Model'!C4) -> 2122909.2 | C4: =(1047456+T11)*(1+'3 Statement Model'!D4) -> 1156138 | D4: =119091+S11 -> 127591 | E4: =(20000)*(1+'3 Statement Model'!E4) -> 20000 | F4: 54545 | G4: =C4+D4 -> 1283729 | H4: =B4-G4 -> 839180.18
A5: 46113 | B5: =(1523636+O12)*(1+'3 Statement Model'!C4) -> 2314363.2 | C5: =(1047456+T12)*(1+'3 Statement Model'!D4) -> 1156138 | D5: 123636 | E5: =(20000)*(1+'3 Statement Model'!E4) -> 20000 | F5: 61818 | G5: =C5+D5 -> 1279774 | H5: =B5-G5 -> 1034589.2
A6: 46143 | B6: =(1548182+O13)*(1+'3 Statement Model'!C4) -> 2505818.4 | C6: =(1047456+T13)*(1+'3 Statement Model'!D4) -> 1156138 | D6: 128182 | E6: =(20000)*(1+'3 Statement Model'!E4) -> 20000 | F6: 69091 | G6: =C6+D6 -> 1284320 | H6: =B6-G6 -> 1221498.4
A7: 46174 | B7: =(1572727+O14)*(1+'3 Statement Model'!C4) -> 2535272.4 | C7: =(1047456+T14)*(1+'3 Statement Model'!D4) -> 1156138 | D7: 132727 | E7: =(20000)*(1+'3 Statement Model'!E4) -> 20000 | F7: 76364 | G7: =C7+D7 -> 1288865 | H7: =B7-G7 -> 1246407.4 | M7: Revenue Drivers | R7: Other OPEX | T7: Payroll cost
A8: 46204 | B8: =(1597273+O15)*(1+'3 Statement Model'!C4) -> 2564727.6 | C8: =(1047456+T15)*(1+'3 Statement Model'!D4) -> 1156138 | D8: 137273 | E8: =(20000)*(1+'3 Statement Model'!E4) -> 20000 | F8: 83636 | G8: =C8+D8 -> 1293411 | H8: =B8-G8 -> 1271316.6 | L8: Month | M8: Effective Sales HC | N8: Revenue Per Rep | R8: Month | S8: Total HR Expansion Cost
A9: 46235 | B9: =(1621818+O16)*(1+'3 Statement Model'!C4) -> 2594181.6 | C9: =(1047456+T16)*(1+'3 Statement Model'!D4) -> 1156138 | D9: 141818 | E9: =(20000)*(1+'3 Statement Model'!E4) -> 20000 | F9: 90909 | G9: =C9+D9 -> 1297956 | H9: =B9-G9 -> 1296225.6 | L9: 46023 | M9: 0 | N9: 90000 | O9: 0 | R9: 46023 | S9: 32140 | T9: 64697.615
A10: 46266 | B10: =(1646364+O17)*(1+'3 Statement Model'!C4) -> 2623636.8 | C10: =(1047456+T17)*(1+'3 Statement Model'!D4) -> 1156138 | D10: 146364 | E10: =(20000)*(1+'3 Statement Model'!E4) -> 20000 | F10: 98182 | G10: =C10+D10 -> 1302502 | H10: =B10-G10 -> 1321134.8 | L10: 46054 | M10: 1.5 | N10: 90000 | O10: 135000 | R10: 46054 | S10: 16500 | T10: 91015.115
A11: 46296 | B11: =(1670909+O18) -> 2210909 | C11: =(1047456+T18)*(1+'3 Statement Model'!D4) -> 1156138 | D11: 150909 | E11: =(20000)*(1+'3 Statement Model'!E4) -> 20000 | F11: 105455 | G11: =C11+D11 -> 1307047 | H11: =B11-G11 -> 903861.98 | L11: 46082 | M11: 3 | N11: 90000 | O11: 270000 | R11: 46082 | S11: 8500 | T11: 108682.02
A12: 46327 | B12: =(1695455+O19)*(1+'3 Statement Model'!C4) -> 2682546 | C12: =(1047456+T19)*(1+'3 Statement Model'!D4) -> 1156138 | D12: 155455 | E12: =(20000)*(1+'3 Statement Model'!E4) -> 20000 | F12: 112727 | G12: =C12+D12 -> 1311593 | H12: =B12-G12 -> 1370953 | L12: 46113 | M12: 4.5 | N12: 90000 | O12: 405000 | R12: 46113 | S12: 0 | T12: 108682.02
A13: 46357 | B13: =(1720000+O20)*(1+'3 Statement Model'!C4) -> 2712000 | C13: =(1047456+T20)*(1+'3 Statement Model'!D4) -> 1156138 | D13: 160000 | E13: =(20000)*(1+'3 Statement Model'!E4) -> 20000 | F13: 120000 | G13: =C13+D13 -> 1316138 | H13: =B13-G13 -> 1395862 | L13: 46143 | M13: 6 | N13: 90000 | O13: 540000 | R13: 46143 | S13: 0 | T13: 108682.02
L14: 46174 | M14: 6 | N14: 90000 | O14: 540000 | R14: 46174 | S14: 0 | T14: 108682.02
L15: 46204 | M15: 6 | N15: 90000 | O15: 540000 | R15: 46204 | S15: 0 | T15: 108682.02
L16: 46235 | M16: 6 | N16: 90000 | O16: 540000 | R16: 46235 | S16: 0 | T16: 108682.02
L17: 46266 | M17: 6 | N17: 90000 | O17: 540000 | R17: 46266 | S17: 0 | T17: 108682.02
L18: 46296 | M18: 6 | N18: 90000 | O18: 540000 | R18: 46296 | S18: 0 | T18: 108682.02
L19: 46327 | M19: 6 | N19: 90000 | O19: 540000 | R19: 46327 | S19: 0 | T19: 108682.02
L20: 46357 | M20: 6 | N20: 90000 | O20: 540000 | R20: 46357 | S20: 0 | T20: 108682.02

Sheet HR Analyst Report
B1: Revenue Drivers | G1: Other OPEX | I1: Payroll cost
A2: Month | B2: Effective Sales HC | C2: Revenue Per Rep | G2: Month | H2: Total HR Expansion Cost
A3: 46023 | B3: 0 | C3: 90000 | D3: 0 | G3: 46023 | H3: 32140 | I3: 64697.615
A4: 46054 | B4: 1.5 | C4: 90000 | D4: 135000 | G4: 46054 | H4: 16500 | I4: 91015.115
A5: 46082 | B5: 3 | C5: 90000 | D5: 270000 | G5: 46082 | H5: 8500 | I5: 108682.02
A6: 46113 | B6: 4.5 | C6: 90000 | D6: 405000 | G6: 46113 | H6: 0 | I6: 108682.02
A7: 46143 | B7: 6 | C7: 90000 | D7: 540000 | G7: 46143 | H7: 0 | I7: 108682.02
A8: 46174 | B8: 6 | C8: 90000 | D8: 540000 | G8: 46174 | H8: 0 | I8: 108682.02
A9: 46204 | B9: 6 | C9: 90000 | D9: 540000 | G9: 46204 | H9: 0 | I9: 108682.02
A10: 46235 | B10: 6 | C10: 90000 | D10: 540000 | G10: 46235 | H10: 0 | I10: 108682.02
A11: 46266 | B11: 6 | C11: 90000 | D11: 540000 | G11: 46266 | H11: 0 | I11: 108682.02
A12: 46296 | B12: 6 | C12: 90000 | D12: 540000 | G12: 46296 | H12: 0 | I12: 108682.02
A13: 46327 | B13: 6 | C13: 90000 | D13: 540000 | G13: 46327 | H13: 0 | I13: 108682.02
A14: 46357 | B14: 6 | C14: 90000 | D14: 540000 | G14: 46357 | H14: 0 | I14: 108682.02

Sheet Financing
A1: Source | B1: Amount | C1: Start_Date | D1: Interest_Rate | E1: Repayment_Period_Months
A2: Loan | B2: 500000 | C2: 46023 | D2: 0.08 | E2: 24
A3: Equity | B3: 200000 | C3: 46023
B6: Loan Repayment Schedule
A7: Monthly Repayment | C7: =PMT(D2/12,E2,-B2) -> 22613.646
A8: Interest | C8: =B2*D2/12 -> 3333.3333
A9: Principal | C9: =C7-C8 -> 19280.312

Sheet CAPEX
A1: Period | B1: CAPEX | C1: Depreciation
A2: 46023 | B2: 200000 | C2: =B2/$I$3 -> 3333.3333
A3: 46054 | B3: 20000 | C3: =B3/$I$3 -> 333.33333 | I3: 60
A4: 46082 | B4: 20000 | C4: =B4/$I$3 -> 333.33333
A5: 46113 | B5: 20000 | C5: =B5/$I$3 -> 333.33333
A6: 46143 | B6: 20000 | C6: =B6/$I$3 -> 333.33333
A7: 46174 | B7: 20000 | C7: =B7/$I$3 -> 333.33333
A8: 46204 | B8: 20000 | C8: =B8/$I$3 -> 333.33333
A9: 46235 | B9: 20000 | C9: =B9/$I$3 -> 333.33333
A10: 46266 | B10: 20000 | C10: =B10/$I$3 -> 333.33333
A11: 46296 | B11: 20000 | C11: =B11/$I$3 -> 333.33333
A12: 46327 | B12: 20000 | C12: =B12/$I$3 -> 333.33333
A13: 46357 | B13: 20000 | C13: =B13/$I$3 -> 333.33333
A17: Monthly Depreciation
A19: 46023 | B19: 46054 | C19: 46082 | D19: 46113 | E19: 46143 | F19: 46174 | G19: 46204 | H19: 46235 | I19: 46266 | J19: 46296 | K19: 46327 | L19: 46357
A20: =C2 -> 3333.3333 | B20: =A20+C3 -> 3666.6667 | C20: =B20+C4 -> 4000 | D20: =C20+C5 -> 4333.3333 | E20: =D20+C6 -> 4666.6667 | F20: =E20+C7 -> 5000 | G20: =F20+C8 -> 5333.3333 | H20: =G20+C9 -> 5666.6667 | I20: =H20+C10 -> 6000 | J20: =I20+C11 -> 6333.3333 | K20: =J20+C12 -> 6666.6667 | L20: =K20+C13 -> 7000
A23: Net Book Value (NBV)
A24: =B2-C2 -> 196666.67 | B24: =A24+B3-B20 -> 213000 | C24: =B24+B4-C20 -> 229000 | D24: =C24+B5-D20 -> 244666.67 | E24: =D24+B6-E20 -> 260000 | F24: =E24+B7-F20 -> 275000 | G24: =F24+B8-G20 -> 289666.67 | H24: =G24+B9-H20 -> 304000 | I24: =H24+B10-I20 -> 318000 | J24: =I24+B11-J20 -> 331666.67 | K24: =J24+B12-K20 -> 345000 | L24: =K24+B13-L20 -> 358000

Sheet OPEX Analysis
B3: Controllable VS Structural Cost | L3: Trend & Variance Analysis
B4: Period | C4: Revenue | D4: Payroll Cost | E4: Other OPEX | F4: Payroll/Revenue | G4: Other OPEX/Revenue | H4: Total OPEX/Revenue | L4: Period | M4: MoM change in Payroll Cost | N4: MoM change in Other OPEX | O4: MoM change in Revenue
B5: 46023 | C5: ='Financial Forecast'!B2 -> 1380000 | D5: ='Financial Forecast'!C2 -> 1112153.6 | E5: ='Financial Forecast'!D2 -> 142140 | F5: =D5/C5 -> 0.80590842 | G5: =E5/C5 -> 0.103 | H5: =(D5+E5)/C5 -> 0.90890842 | L5: 46023 | M5: =0 -> 0 | N5: 0 | O5: 0
B6: 46054 | C6: ='Financial Forecast'!B3 -> 1931454 | D6: ='Financial Forecast'!C3 -> 1138471.1 | E6: ='Financial Forecast'!D3 -> 131045 | F6: =D6/C6 -> 0.58943734 | G6: =E6/C6 -> 0.067847849 | H6: =(D6+E6)/C6 -> 0.65728519 | L6: 46054 | M6: =(D6-D5)/D5 -> 0.023663548 | N6: =(E6-E5)/E5 -> -0.078056845 | O6: =(C6-C5)/C5 -> 0.39960435
B7: 46082 | C7: ='Financial Forecast'!B4 -> 2122909.2 | D7: ='Financial Forecast'!C4 -> 1156138 | E7: ='Financial Forecast'!D4 -> 127591 | F7: =D7/C7 -> 0.54460079 | G7: =E7/C7 -> 0.060101958 | H7: =(D7+E7)/C7 -> 0.60470274 | L7: 46082 | M7: =(D7-D6)/D6 -> 0.015518095 | N7: =(E7-E6)/E6 -> -0.026357358 | O7: =(C7-C6)/C6 -> 0.099124908
B8: 46113 | C8: ='Financial Forecast'!B5 -> 2314363.2 | D8: ='Financial Forecast'!C5 -> 1156138 | E8: ='Financial Forecast'!D5 -> 123636 | F8: =D8/C8 -> 0.49954908 | G8: =E8/C8 -> 0.053421174 | H8: =(D8+E8)/C8 -> 0.55297026 | L8: 46113 | M8: =(D8-D7)/D7 -> 0 | N8: =(E8-E7)/E7 -> -0.030997484 | O8: =(C8-C7)/C7 -> 0.090184733
B9: 46143 | C9: ='Financial Forecast'!B6 -> 2505818.4 | D9: ='Financial Forecast'!C6 -> 1156138 | E9: ='Financial Forecast'!D6 -> 128182 | F9: =D9/C9 -> 0.46138141 | G9: =E9/C9 -> 0.051153747 | H9: =(D9+E9)/C9 -> 0.51253515 | L9: 46143 | M9: =(D9-D8)/D8 -> 0 | N9: =(E9-E8)/E8 -> 0.036769226 | O9: =(C9-C8)/C8 -> 0.082724786
B10: 46174 | C10: ='Financial Forecast'!B7 -> 2535272.4 | D10: ='Financial Forecast'!C7 -> 1156138 | E10: ='Financial Forecast'!D7 -> 132727 | F10: =D10/C10 -> 0.45602122 | G10: =E10/C10 -> 0.052352165 | H10: =(D10+E10)/C10 -> 0.50837339 | L10: 46174 | M10: =(D10-D9)/D9 -> 0 | N10: =(E10-E9)/E9 -> 0.035457397 | O10: =(C10-C9)/C9 -> 0.011754244
B11: 46204 | C11: ='Financial Forecast'!B8 -> 2564727.6 | D11: ='Financial Forecast'!C8 -> 1156138 | E11: ='Financial Forecast'!D8 -> 137273 | F11: =D11/C11 -> 0.45078394 | G11: =E11/C11 -> 0.053523423 | H11: =(D11+E11)/C11 -> 0.50430737 | L11: 46204 | M11: =(D11-D10)/D10 -> 0 | N11: =(E11-E10)/E10 -> 0.034250755 | O11: =(C11-C10)/C10 -> 0.01161816
B12: 46235 | C12: ='Financial Forecast'!B9 -> 2594181.6 | D12: ='Financial Forecast'!C9 -> 1156138 | E12: ='Financial Forecast'!D9 -> 141818 | F12: =D12/C12 -> 0.4456658 | G12: =E12/C12 -> 0.054667723 | H12: =(D12+E12)/C12 -> 0.50033352 | L12: 46235 | M12: =(D12-D11)/D11 -> 0 | N12: =(E12-E11)/E11 -> 0.033109206 | O12: =(C12-C11)/C11 -> 0.011484261
B13: 46266 | C13: ='Financial Forecast'!B10 -> 2623636.8 | D13: ='Financial Forecast'!C10 -> 1156138 | E13: ='Financial Forecast'!D10 -> 146364 | F13: =D13/C13 -> 0.44066237 | G13: =E13/C13 -> 0.055786685 | H13: =(D13+E13)/C13 -> 0.49644906 | L13: 46266 | M13: =(D13-D12)/D12 -> 0 | N13: =(E13-E12)/E12 -> 0.032055169 | O13: =(C13-C12)/C12 -> 0.011354332
B14: 46296 | C14: ='Financial Forecast'!B11 -> 2210909 | D14: ='Financial Forecast'!C11 -> 1156138 | E14: ='Financial Forecast'!D11 -> 150909 | F14: =D14/C14 -> 0.52292429 | G14: =E14/C14 -> 0.068256541 | H14: =(D14+E14)/C14 -> 0.59118083 | L14: 46296 | M14: =(D14-D13)/D13 -> 0 | N14: =(E14-E13)/E13 -> 0.031052718 | O14: =(C14-C13)/C13 -> -0.15731133
B15: 46327 | C15: ='Financial Forecast'!B12 -> 2682546 | D15: ='Financial Forecast'!C12 -> 1156138 | E15: ='Financial Forecast'!D12 -> 155455 | F15: =D15/C15 -> 0.43098535 | G15: =E15/C15 -> 0.057950544 | H15: =(D15+E15)/C15 -> 0.48893589 | L15: 46327 | M15: =(D15-D14)/D14 -> 0 | N15: =(E15-E14)/E14 -> 0.030124115 | O15: =(C15-C14)/C14 -> 0.21332267
B16: 46357 | C16: ='Financial Forecast'!B13 -> 2712000 | D16: ='Financial Forecast'!C13 -> 1156138 | E16: ='Financial Forecast'!D13 -> 160000 | F16: =D16/C16 -> 0.42630458 | G16: =E16/C16 -> 0.05899705 | H16: =(D16+E16)/C16 -> 0.48530163 | L16: 46357 | M16: =(D16-D15)/D15 -> 0 | N16: =(E16-E15)/E15 -> 0.029236757 | O16: =(C16-C15)/C15 -> 0.010979868
B19: Cost Efficiency Diagnistics
B20: Period | C20: Revenue | D20: Payroll Cost | E20: Other OPEX | F20: EBITDA | G20: Revenue per payroll | H20: Revenue per OPEX | I20: EBITDA Margin
B21: 46023 | C21: 1150000 | D21: 1112153.6 | E21: 142140 | F21: ='Financial Forecast'!H2 -> 125706.39 | G21: =C21/D21 -> 1.0340298 | H21: =C21/(D21+E21) -> 0.91685072 | I21: =F21/C21 -> 0.1093099
B22: 46054 | C22: 1609545 | D22: 1138471.1 | E22: 131045 | F22: ='Financial Forecast'!H3 -> 661937.89 | G22: =C22/D22 -> 1.4137776 | H22: =C22/(D22+E22) -> 1.2678413 | I22: =F22/C22 -> 0.41125777
B23: 46082 | C23: 1769091 | D23: 1156138 | E23: 127591 | F23: ='Financial Forecast'!H4 -> 839180.18 | G23: =C23/D23 -> 1.5301728 | H23: =C23/(D23+E23) -> 1.3780876 | I23: =F23/C23 -> 0.47435671
B24: 46113 | C24: 1928636 | D24: 1156138 | E24: 123636 | F24: ='Financial Forecast'!H5 -> 1034589.2 | G24: =C24/D24 -> 1.6681711 | H24: =C24/(D24+E24) -> 1.5070129 | I24: =F24/C24 -> 0.53643569
B25: 46143 | C25: 2088182 | D25: 1156138 | E25: 128182 | F25: ='Financial Forecast'!H6 -> 1221498.4 | G25: =C25/D25 -> 1.8061702 | H25: =C25/(D25+E25) -> 1.6259047 | I25: =F25/C25 -> 0.58495782
B26: 46174 | C26: 2112727 | D26: 1156138 | E26: 132727 | F26: ='Financial Forecast'!H7 -> 1246407.4 | G26: =C26/D26 -> 1.8274003 | H26: =C26/(D26+E26) -> 1.6392151 | I26: =F26/C26 -> 0.58995193
B27: 46204 | C27: 2137273 | D27: 1156138 | E27: 137273 | F27: ='Financial Forecast'!H8 -> 1271316.6 | G27: =C27/D27 -> 1.8486314 | H27: =C27/(D27+E27) -> 1.6524314 | I27: =F27/C27 -> 0.59483116
B28: 46235 | C28: 2161818 | D28: 1156138 | E28: 141818 | F28: ='Financial Forecast'!H9 -> 1296225.6 | G28: =C28/D28 -> 1.8698615 | H28: =C28/(D28+E28) -> 1.6655557 | I28: =F28/C28 -> 0.59959977
B29: 46266 | C29: 2186364 | D29: 1156138 | E29: 146364 | F29: ='Financial Forecast'!H10 -> 1321134.8 | G29: =C29/D29 -> 1.8910926 | H29: =C29/(D29+E29) -> 1.6785878 | I29: =F29/C29 -> 0.60426113
B30: 46296 | C30: 2210909 | D30: 1156138 | E30: 150909 | F30: ='Financial Forecast'!H11 -> 903861.98 | G30: =C30/D30 -> 1.9123227 | H30: =C30/(D30+E30) -> 1.6915298 | I30: =F30/C30 -> 0.40881917
B31: 46327 | C31: 2235455 | D31: 1156138 | E31: 155455 | F31: ='Financial Forecast'!H12 -> 1370953 | G31: =C31/D31 -> 1.9335537 | H31: =C31/(D31+E31) -> 1.7043816 | I31: =F31/C31 -> 0.61327693
B32: 46357 | C32: 2260000 | D32: 1156138 | E32: 160000 | F32: ='Financial Forecast'!H13 -> 1395862 | G32: =C32/D32 -> 1.9547839 | H32: =C32/(D32+E32) -> 1.7171451 | I32: =F32/C32 -> 0.61763804

Sheet Liquidity and Risk Analysis
A2: Period | B2: Opening Cash | C2: Net Cash Move | D2: Closing Cash | E2: Risk Flag
A3: 46023
A4: 46054
A5: 46082
A6: 46113
A7: 46143
A8: 46174
A9: 46204
A10: 46235
A11: 46266
A12: 46296
A13: 46327
A14: 46357

Sheet CAPEX Investment Analysis
C3: CAPEX Timing & Intensity Review | K3: CAPEX Coverage Test
B4: Period | C4: Revenue | D4: CAPEX | E4: EBITDA | F4: CAPEX/Revenue | G4: CAPEX/EBITDA | J4: Period | K4: Operating Cash Flow | L4: CAPEX | M4: Cash Coverage Flag
B5: 46023 | C5: ='Financial Forecast'!B2 -> 1380000 | D5: ='Financial Forecast'!E2 -> 200000 | E5: ='Financial Forecast'!H2 -> 125706.39 | F5: =D5/C5 -> 0.14492754 | G5: =D5/E5 -> 1.5910091 | J5: 46023 | K5: ='Financial Forecast'!F2 -> -140000 | L5: =D5 -> 200000 | M5: =IF(K5>=L5, "OK","Liquidity Risk") -> Liquidity Risk
B6: 46054 | C6: ='Financial Forecast'!B3 -> 1931454 | D6: ='Financial Forecast'!E3 -> 20000 | E6: ='Financial Forecast'!H3 -> 661937.89 | F6: =D6/C6 -> 0.010354893 | G6: =D6/E6 -> 0.030214315 | J6: 46054 | K6: ='Financial Forecast'!F3 -> 47273 | L6: =D6 -> 20000 | M6: =IF(K6>=L6, "OK","Liquidity Risk") -> OK
B7: 46082 | C7: ='Financial Forecast'!B4 -> 2122909.2 | D7: ='Financial Forecast'!E4 -> 20000 | E7: ='Financial Forecast'!H4 -> 839180.18 | F7: =D7/C7 -> 0.0094210341 | G7: =D7/E7 -> 0.023832784 | J7: 46082 | K7: ='Financial Forecast'!F4 -> 54545 | L7: =D7 -> 20000 | M7: =IF(K7>=L7, "OK","Liquidity Risk") -> OK
B8: 46113 | C8: ='Financial Forecast'!B5 -> 2314363.2 | D8: ='Financial Forecast'!E5 -> 20000 | E8: ='Financial Forecast'!H5 -> 1034589.2 | F8: =D8/C8 -> 0.008641686 | G8: =D8/E8 -> 0.019331345 | J8: 46113 | K8: ='Financial Forecast'!F5 -> 61818 | L8: =D8 -> 20000 | M8: =IF(K8>=L8, "OK","Liquidity Risk") -> OK
B9: 46143 | C9: ='Financial Forecast'!B6 -> 2505818.4 | D9: ='Financial Forecast'!E6 -> 20000 | E9: ='Financial Forecast'!H6 -> 1221498.4 | F9: =D9/C9 -> 0.0079814244 | G9: =D9/E9 -> 0.016373333 | J9: 46143 | K9: ='Financial Forecast'!F6 -> 69091 | L9: =D9 -> 20000 | M9: =IF(K9>=L9, "OK","Liquidity Risk") -> OK
B10: 46174 | C10: ='Financial Forecast'!B7 -> 2535272.4 | D10: ='Financial Forecast'!E7 -> 20000 | E10: ='Financial Forecast'!H7 -> 1246407.4 | F10: =D10/C10 -> 0.0078886987 | G10: =D10/E10 -> 0.016046118 | J10: 46174 | K10: ='Financial Forecast'!F7 -> 76364 | L10: =D10 -> 20000 | M10: =IF(K10>=L10, "OK","Liquidity Risk") -> OK
B11: 46204 | C11: ='Financial Forecast'!B8 -> 2564727.6 | D11: ='Financial Forecast'!E8 -> 20000 | E11: ='Financial Forecast'!H8 -> 1271316.6 | F11: =D11/C11 -> 0.0077980991 | G11: =D11/E11 -> 0.015731723 | J11: 46204 | K11: ='Financial Forecast'!F8 -> 83636 | L11: =D11 -> 20000 | M11: =IF(K11>=L11, "OK","Liquidity Risk") -> OK
B12: 46235 | C12: ='Financial Forecast'!B9 -> 2594181.6 | D12: ='Financial Forecast'!E9 -> 20000 | E12: ='Financial Forecast'!H9 -> 1296225.6 | F12: =D12/C12 -> 0.0077095605 | G12: =D12/E12 -> 0.015429413 | J12: 46235 | K12: ='Financial Forecast'!F9 -> 90909 | L12: =D12 -> 20000 | M12: =IF(K12>=L12, "OK","Liquidity Risk") -> OK
B13: 46266 | C13: ='Financial Forecast'!B10 -> 2623636.8 | D13: ='Financial Forecast'!E10 -> 20000 | E13: ='Financial Forecast'!H10 -> 1321134.8 | F13: =D13/C13 -> 0.0076230064 | G13: =D13/E13 -> 0.015138501 | J13: 46266 | K13: ='Financial Forecast'!F10 -> 98182 | L13: =D13 -> 20000 | M13: =IF(K13>=L13, "OK","Liquidity Risk") -> OK
B14: 46296 | C14: ='Financial Forecast'!B11 -> 2210909 | D14: ='Financial Forecast'!E11 -> 20000 | E14: ='Financial Forecast'!H11 -> 903861.98 | F14: =D14/C14 -> 0.009046053 | G14: =D14/E14 -> 0.022127272 | J14: 46296 | K14: ='Financial Forecast'!F11 -> 105455 | L14: =D14 -> 20000 | M14: =IF(K14>=L14, "OK","Liquidity Risk") -> OK
B15: 46327 | C15: ='Financial Forecast'!B12 -> 2682546 | D15: ='Financial Forecast'!E12 -> 20000 | E15: ='Financial Forecast'!H12 -> 1370953 | F15: =D15/C15 -> 0.0074556037 | G15: =D15/E15 -> 0.014588392 | J15: 46327 | K15: ='Financial Forecast'!F12 -> 112727 | L15: =D15 -> 20000 | M15: =IF(K15>=L15, "OK","Liquidity Risk") -> OK
B16: 46357 | C16: ='Financial Forecast'!B13 -> 2712000 | D16: ='Financial Forecast'!E13 -> 20000 | E16: ='Financial Forecast'!H13 -> 1395862 | F16: =D16/C16 -> 0.0073746313 | G16: =D16/E16 -> 0.014328064 | J16: 46357 | K16: ='Financial Forecast'!F13 -> 120000 | L16: =D16 -> 20000 | M16: =IF(K16>=L16, "OK","Liquidity Risk") -> OK
C19: Investment Feasibility
B20: Period | C20: CAPEX | D20: EBITDA | E20: Commulative CAPEX | F20: Commulated EBITDA | G20: Payback
B21: 46023 | C21: =D5 -> 200000 | D21: =E5 -> 125706.39 | E21: =C21 -> 200000 | F21: =D21 -> 125706.39 | G21: =IF(F21>=E21,"Yes","No") -> No
B22: 46054 | C22: =D6 -> 20000 | D22: =E6 -> 661937.89 | E22: =C22+E21 -> 220000 | F22: =D22+F21 -> 787644.27 | G22: =IF(F22>=E22,"Yes","No") -> Yes
B23: 46082 | C23: =D7 -> 20000 | D23: =E7 -> 839180.18 | E23: =C23+E22 -> 240000 | F23: =D23+F22 -> 1626824.5 | G23: =IF(F23>=E23,"Yes","No") -> Yes
B24: 46113 | C24: =D8 -> 20000 | D24: =E8 -> 1034589.2 | E24: =C24+E23 -> 260000 | F24: =D24+F23 -> 2661413.6 | G24: =IF(F24>=E24,"Yes","No") -> Yes
B25: 46143 | C25: =D9 -> 20000 | D25: =E9 -> 1221498.4 | E25: =C25+E24 -> 280000 | F25: =D25+F24 -> 3882912 | G25: =IF(F25>=E25,"Yes","No") -> Yes
B26: 46174 | C26: =D10 -> 20000 | D26: =E10 -> 1246407.4 | E26: =C26+E25 -> 300000 | F26: =D26+F25 -> 5129319.4 | G26: =IF(F26>=E26,"Yes","No") -> Yes
B27: 46204 | C27: =D11 -> 20000 | D27: =E11 -> 1271316.6 | E27: =C27+E26 -> 320000 | F27: =D27+F26 -> 6400636 | G27: =IF(F27>=E27,"Yes","No") -> Yes
B28: 46235 | C28: =D12 -> 20000 | D28: =E12 -> 1296225.6 | E28: =C28+E27 -> 340000 | F28: =D28+F27 -> 7696861.6 | G28: =IF(F28>=E28,"Yes","No") -> Yes
B29: 46266 | C29: =D13 -> 20000 | D29: =E13 -> 1321134.8 | E29: =C29+E28 -> 360000 | F29: =D29+F28 -> 9017996.3 | G29: =IF(F29>=E29,"Yes","No") -> Yes
B30: 46296 | C30: =D14 -> 20000 | D30: =E14 -> 903861.98 | E30: =C30+E29 -> 380000 | F30: =D30+F29 -> 9921858.3 | G30: =IF(F30>=E30,"Yes","No") -> Yes
B31: 46327 | C31: =D15 -> 20000 | D31: =E15 -> 1370953 | E31: =C31+E30 -> 400000 | F31: =D31+F30 -> 11292811 | G31: =IF(F31>=E31,"Yes","No") -> Yes
B32: 46357 | C32: =D16 -> 20000 | D32: =E16 -> 1395862 | E32: =C32+E31 -> 420000 | F32: =D32+F31 -> 12688673 | G32: =IF(F32>=E32,"Yes","No") -> Yes

Sheet Assumptions
A1: Assumptions
B2: Revenue | C2: Payroll | D2: CAPEX
A3: Best | B3: 0.2 | C3: 0 | D3: 0
A4: Base | B4: 0 | C4: 0 | D4: 0
A5: Worst | B5: -0.2 | C5: 0.1 | D5: 0.1
